pypstools/__init__.py
pypstools/analysis.py
pypstools/digsilent_simulation.py
pypstools/dynamics.py
pypstools/hickle.py
pypstools/models2dict.py
pypstools/psse_simulation.py
pypstools/publisher.py
pypstools/rst_tools.py
pypstools/swissgrid.py
pypstools/tests_linux.py
pypstools/todo_old_code.py
pypstools/tools.py
pypstools-0.2.5.dist-info/DESCRIPTION.rst
pypstools-0.2.5.dist-info/METADATA
pypstools-0.2.5.dist-info/RECORD
pypstools-0.2.5.dist-info/WHEEL
pypstools-0.2.5.dist-info/metadata.json
pypstools-0.2.5.dist-info/top_level.txt
